hsutilities/__init__.py
hsutilities/admin.py
hsutilities/domains.py
hsutilities/users.py
hsutilities-0.1.4.dist-info/LICENSE
hsutilities-0.1.4.dist-info/METADATA
hsutilities-0.1.4.dist-info/WHEEL
hsutilities-0.1.4.dist-info/top_level.txt
hsutilities-0.1.4.dist-info/RECORD
