Metadata-Version: 2.1
Name: hsutilities
Version: 0.1.4
Summary: Useful functions for hosting with Hostsharing eG
Home-page: https://github.com/tpokorra/hsutilities
Author: Timotheus Pokorra
Author-email: timotheus.pokorra@solidcharity.com
License: New BSD License
Classifier: Development Status :: 4 - Beta
Classifier: Environment :: Console
Classifier: Environment :: Web Environment
Classifier: Intended Audience :: Developers
Classifier: License :: OSI Approved :: BSD License
Classifier: Programming Language :: Python
Classifier: Programming Language :: Python :: 3 :: Only
License-File: LICENSE
Requires-Dist: hs.admin.api
